{
  "headers": {
    "date": "Wed, 27 May 2026 08:53:46 GMT",
    "content-type": "application/json;charset=utf-8",
    "content-length": "5959",
    "connection": "keep-alive",
    "keep-alive": "timeout=25",
    "vary": "Accept-Encoding",
    "access-control-allow-origin": "*",
    "access-control-expose-headers": "*",
    "x-acs-request-id": "167EA7BD-FFE6-5F00-AAFB-15B29BD128A3",
    "x-acs-trace-id": "0fb6afafe62fd20854123830bd6bff3c",
    "etag": "5NsZo9aIrHEHKTfgNqofi8g5"
  },
  "statusCode": 200,
  "body": {
    "Data": "{\"algo_version\":\"2ca123f830dad3b81e147de7213b2e49afd8cd2f\",\"page_list\":[{\"angle\":0,\"doc_index\":1,\"height\":3456,\"orgHeight\":3456,\"orgWidth\":3456,\"page_id\":0,\"subject_list\":[{\"content_list_info\":[{\"doc_index\":1,\"pos\":[{\"x\":772,\"y\":38},{\"x\":2909,\"y\":166},{\"x\":2858,\"y\":2518},{\"x\":599,\"y\":2534}]}],\"ids\":[],\"is_multipage\":false,\"prism_wordsInfo\":[{\"pos\":[{\"x\":864,\"y\":411},{\"x\":927,\"y\":411},{\"x\":927,\"y\":481},{\"x\":864,\"y\":481}],\"recClassify\":0,\"word\":\"L\"},{\"pos\":[{\"x\":961,\"y\":409},{\"x\":1597,\"y\":487},{\"x\":1584,\"y\":588},{\"x\":948,\"y\":510}],\"recClassify\":2,\"word\":\"25×4=100\"},{\"pos\":[{\"x\":851,\"y\":515},{\"x\":1426,\"y\":591},{\"x\":1413,\"y\":690},{\"x\":838,\"y\":615}],\"recClassify\":2,\"word\":\"3.125×8=\"},{\"pos\":[{\"x\":1183,\"y\":560},{\"x\":1678,\"y\":616},{\"x\":1665,\"y\":733},{\"x\":1170,\"y\":677}],\"recClassify\":2,\"word\":\"×8=1000\"},{\"pos\":[{\"x\":1948,\"y\":519},{\"x\":2637,\"y\":526},{\"x\":2636,\"y\":629},{\"x\":1947,\"y\":621}],\"recClassify\":0,\"word\":\"2360÷9=4\"},{\"pos\":[{\"x\":1948,\"y\":519},{\"x\":2637,\"y\":526},{\"x\":2636,\"y\":629},{\"x\":1947,\"y\":621}],\"recClassify\":0,\"word\":\"2360÷9=4\"},{\"pos\":[{\"x\":793,\"y\":624},{\"x\":1423,\"y\":698},{\"x\":1411,\"y\":801},{\"x\":781,\"y\":726}],\"recClassify\":2,\"word\":\"5.36×2=\"},{\"pos\":[{\"x\":1959,\"y\":634},{\"x\":2649,\"y\":636},{\"x\":2649,\"y\":742},{\"x\":1958,\"y\":741}],\"recClassify\":2,\"word\":\"4.480÷60=7\"},{\"pos\":[{\"x\":1495,\"y\":720},{\"x\":1589,\"y\":720},{\"x\":1589,\"y\":820},{\"x\":1495,\"y\":820}],\"recClassify\":2,\"word\":\"2\"},{\"pos\":[{\"x\":1986,\"y\":742},{\"x\":2704,\"y\":741},{\"x\":2704,\"y\":859},{\"x\":1986,\"y\":860}],\"recClassify\":2,\"word\":\"6.810÷9=90\"},{\"pos\":[{\"x\":908,\"y\":1028},{\"x\":1353,\"y\":1068},{\"x\":1344,\"y\":1169},{\"x\":899,\"y\":1129}],\"recClassify\":2,\"word\":\"308×25\"},{\"pos\":[{\"x\":2169,\"y\":1109},{\"x\":2553,\"y\":1104},{\"x\":2554,\"y\":1203},{\"x\":2170,\"y\":1208}],\"recClassify\":2,\"word\":\"450×36\"},{\"pos\":[{\"x\":758,\"y\":1179},{\"x\":823,\"y\":1179},{\"x\":823,\"y\":1261},{\"x\":758,\"y\":1261}],\"recClassify\":0,\"word\":\"一\"},{\"pos\":[{\"x\":822,\"y\":1155},{\"x\":1555,\"y\":1199},{\"x\":1548,\"y\":1306},{\"x\":815,\"y\":1261}],\"recClassify\":2,\"word\":\"=(300+8)×25\"},{\"pos\":[{\"x\":2098,\"y\":1217},{\"x\":2855,\"y\":1207},{\"x\":2856,\"y\":1320},{\"x\":2100,\"y\":1330}],\"recClassify\":2,\"word\":\"=(500-50)×36\"},{\"pos\":[{\"x\":830,\"y\":1289},{\"x\":1677,\"y\":1333},{\"x\":1672,\"y\":1436},{\"x\":824,\"y\":1391}],\"recClassify\":2,\"word\":\"=300×25+8×25\"},{\"pos\":[{\"x\":2098,\"y\":1336},{\"x\":2980,\"y\":1330},{\"x\":2980,\"y\":1441},{\"x\":2099,\"y\":1447}],\"recClassify\":2,\"word\":\"=500×36-50×36\"},{\"pos\":[{\"x\":827,\"y\":1415},{\"x\":1418,\"y\":1432},{\"x\":1414,\"y\":1545},{\"x\":823,\"y\":1528}],\"recClassify\":2,\"word\":\"=7500+100\"},{\"pos\":[{\"x\":2066,\"y\":1462},{\"x\":2891,\"y\":1462},{\"x\":2891,\"y\":1551},{\"x\":2066,\"y\":1551}],\"recClassify\":2,\"word\":\"=18000-1800\"},{\"pos\":[{\"x\":811,\"y\":1528},{\"x\":1186,\"y\":1528},{\"x\":1186,\"y\":1650},{\"x\":811,\"y\":1651}],\"recClassify\":2,\"word\":\"=7600\"},{\"pos\":[{\"x\":2055,\"y\":1580},{\"x\":2492,\"y\":1577},{\"x\":2493,\"y\":1678},{\"x\":2056,\"y\":1681}],\"recClassify\":2,\"word\":\"=16860\"},{\"pos\":[{\"x\":951,\"y\":1802},{\"x\":1903,\"y\":1796},{\"x\":1904,\"y\":1920},{\"x\":952,\"y\":1925}],\"recClassify\":2,\"word\":\"782÷26=30...2\"},{\"pos\":[{\"x\":2255,\"y\":1797},{\"x\":2928,\"y\":1802},{\"x\":2927,\"y\":1948},{\"x\":2254,\"y\":1943}],\"recClassify\":2,\"word\":\"960÷40=24\"},{\"pos\":[{\"x\":884,\"y\":1960},{\"x\":1320,\"y\":1953},{\"x\":1323,\"y\":2136},{\"x\":887,\"y\":2143}],\"recClassify\":2,\"word\":\"26//782\"},{\"pos\":[{\"x\":2165,\"y\":2020},{\"x\":2385,\"y\":2019},{\"x\":2385,\"y\":2123},{\"x\":2165,\"y\":2124}],\"recClassify\":2,\"word\":\"407\"},{\"pos\":[{\"x\":2432,\"y\":1973},{\"x\":2496,\"y\":1973},{\"x\":2496,\"y\":2055},{\"x\":2432,\"y\":2055}],\"recClassify\":0,\"word\":\"。\"},{\"pos\":[{\"x\":2465,\"y\":1939},{\"x\":2612,\"y\":1939},{\"x\":2612,\"y\":2051},{\"x\":2465,\"y\":2051}],\"recClassify\":2,\"word\":\"24\"},{\"pos\":[{\"x\":2471,\"y\":2046},{\"x\":2549,\"y\":2046},{\"x\":2549,\"y\":2110},{\"x\":2471,\"y\":2110}],\"recClassify\":0,\"word\":\"6\"},{\"pos\":[{\"x\":2525,\"y\":2045},{\"x\":2577,\"y\":2045},{\"x\":2577,\"y\":2117},{\"x\":2525,\"y\":2117}],\"recClassify\":0,\"word\":\"D\"},{\"pos\":[{\"x\":1069,\"y\":2135},{\"x\":1210,\"y\":2135},{\"x\":1210,\"y\":2250},{\"x\":1069,\"y\":2250}],\"recClassify\":2,\"word\":\"78\"},{\"pos\":[{\"x\":2388,\"y\":2129},{\"x\":2441,\"y\":2129},{\"x\":2441,\"y\":2222},{\"x\":2388,\"y\":2222}],\"recClassify\":2,\"word\":\"8\"},{\"pos\":[{\"x\":2392,\"y\":2194},{\"x\":2590,\"y\":2196},{\"x\":2589,\"y\":2295},{\"x\":2391,\"y\":2293}],\"recClassify\":2,\"word\":\"160\"},{\"pos\":[{\"x\":1186,\"y\":2289},{\"x\":1293,\"y\":2289},{\"x\":1293,\"y\":2439},{\"x\":1186,\"y\":2439}],\"recClassify\":2,\"word\":\"2&\"},{\"pos\":[{\"x\":2400,\"y\":2293},{\"x\":2569,\"y\":2293},{\"x\":2569,\"y\":2388},{\"x\":2400,\"y\":2388}],\"recClassify\":2,\"word\":\"160\"},{\"pos\":[{\"x\":2536,\"y\":2420},{\"x\":2605,\"y\":2420},{\"x\":2605,\"y\":2493},{\"x\":2536,\"y\":2493}],\"recClassify\":2,\"word\":\"0\"},{\"pos\":[{\"x\":2580,\"y\":2429},{\"x\":2633,\"y\":2429},{\"x\":2633,\"y\":2494},{\"x\":2580,\"y\":2494}],\"recClassify\":0,\"word\":\">\"}],\"text\":\"L 25×4=100 3.125×8= ×8=1000 2360÷9=4 2360÷9=4 5.36×2= 4.480÷60=7 2 6.810÷9=90 308×25 450×36 一 =(300+8)×25 =(500-50)×36 =300×25+8×25 =500×36-50×36 =7500+100 =18000-1800 =7600 =16860 782÷26=30...2 960÷40=24 26//782 407 。 24 6 D 78 8 160 2& 160 0 > \"}],\"width\":3456}]}",
    "RequestId": "167EA7BD-FFE6-5F00-AAFB-15B29BD128A3"
  }
}